.gitignore
CHANGELOG.md
LICENSE
MANIFEST.in
README.md
buildout.cfg
setup.py
src/aim/__init__.py
src/aim.models.egg-info/PKG-INFO
src/aim.models.egg-info/SOURCES.txt
src/aim.models.egg-info/dependency_links.txt
src/aim.models.egg-info/not-zip-safe
src/aim.models.egg-info/requires.txt
src/aim.models.egg-info/top_level.txt
src/aim/models/__init__.py
src/aim/models/accounts.py
src/aim/models/applications.py
src/aim/models/base.py
src/aim/models/cfn_init.py
src/aim/models/events.py
src/aim/models/exceptions.py
src/aim/models/formatter.py
src/aim/models/iam.py
src/aim/models/loader.py
src/aim/models/locations.py
src/aim/models/logging.py
src/aim/models/metrics.py
src/aim/models/networks.py
src/aim/models/project.py
src/aim/models/references.py
src/aim/models/resources.py
src/aim/models/schemas.py
src/aim/models/services.py
src/aim/models/storages.py
src/aim/models/vocabulary.py
src/aim/models/yaml.py
src/aim/models/tests/__init__.py
src/aim/models/tests/test_loader.py