Metadata-Version: 2.1
Name: aim.models
Version: 6.1.0
Summary: aim.models: Semantic cloud infrastructure configuration file format and object model
Home-page: https://github.com/waterbear-cloud/aim.models
Author: Waterbear Cloud
Author-email: hello@waterbear.cloud
License: UNKNOWN
Keywords: AWS,Cloud,Infrastructure-as-Code
Platform: UNKNOWN
Classifier: License :: OSI Approved :: Mozilla Public License 2.0 (MPL 2.0)
Classifier: Development Status :: 5 - Production/Stable
